gcp_profiles/__init__.py
gcp_profiles/main.py
gcp_profiles/py.typed
gcp_profiles/utils.py
gcp_profiles/vault.py
gcp_profiles-0.1.0.dist-info/WHEEL
gcp_profiles-0.1.0.dist-info/entry_points.txt
gcp_profiles-0.1.0.dist-info/METADATA
gcp_profiles-0.1.0.dist-info/RECORD
