Metadata-Version: 2.3
Name: gcp-profiles
Version: 0.1.0
Summary: A simple gcloud auth and adc manager.
Author: Manel Caireta
Author-email: Manel Caireta <manelkireta@gmail.com>
License: MIT License
Requires-Dist: rich>=14.2.0
Requires-Dist: typer>=0.20.0
Requires-Python: >=3.10
